qspin/__init__.py
qspin/jones.py
qspin/qspin.py
qspin-2.3.3.dist-info/LICENSE.txt
qspin-2.3.3.dist-info/METADATA
qspin-2.3.3.dist-info/WHEEL
qspin-2.3.3.dist-info/top_level.txt
qspin-2.3.3.dist-info/RECORD
