Metadata-Version: 2.1
Name: qspin
Version: 2.3.3
Summary: Learn quantum spin, entanglement, and quantum computer operations
Home-page: https://bitbucket.org/donald_gavel/qspin
Download-URL: https://bitbucket.org/donald_gavel/qspin/downloads
Author: Don Gavel
Author-email: donald.gavel@gmail.com
Keywords: quantum,spin,electron,qubit,quantum computing,entanglement,entropy
Classifier: Development Status :: 5 - Production/Stable
Classifier: Intended Audience :: Science/Research
Classifier: Intended Audience :: Information Technology
Classifier: License :: OSI Approved :: MIT License
Classifier: Programming Language :: Python :: 3
Classifier: Topic :: Scientific/Engineering :: Physics
Classifier: Operating System :: MacOS
Classifier: Operating System :: POSIX :: Linux
Classifier: Operating System :: Unix
Classifier: Operating System :: Microsoft :: Windows
License-File: LICENSE.txt
Requires-Dist: numpy
Requires-Dist: scipy
